geogrids/__init__.py
geogrids/encoders/__init__.py
geogrids/encoders/encoder.py
geogrids/encoders/wordlists.py
geogrids/gdgg/__init__.py
geogrids/gdgg/oqtm.py
geogrids-1.1.0.dist-info/LICENSE
geogrids-1.1.0.dist-info/METADATA
geogrids-1.1.0.dist-info/WHEEL
geogrids-1.1.0.dist-info/top_level.txt
geogrids-1.1.0.dist-info/RECORD
