Metadata-Version: 2.1
Name: geogrids
Version: 1.1.0
Summary: A Python implementation of the npm geogrids library - utilities for working with Global Discrete Geodetic Grids (GDGGs)
Home-page: https://github.com/om-henners/geogrids
Author: Henry Walshaw
Author-email: henry.walshaw@gmail.com
License: WTFPL
Platform: UNKNOWN
Classifier: Development Status :: 5 - Production/Stable
Classifier: Programming Language :: Python :: 3
Classifier: Programming Language :: Python :: 3.5
Classifier: Programming Language :: Python :: 3.6
Classifier: Programming Language :: Python :: 3.7
Classifier: Topic :: Scientific/Engineering :: GIS
